[
  { "id": 1, "name": "ржорж┐ржирж┐ржХрзЗржЯ ржЪрж╛рж▓ (рж╕рзБржкрж╛рж░)", "category": "ржЪрж╛рж▓", "price": 72, "image": "ЁЯМ╛", "origin": "ржиржУржЧрж╛ржБ", "stock": "рзлрзжрзжрзж ржХрзЗржЬрж┐", "rating": 5 },
  { "id": 2, "name": "ржирж╛ржЬрж┐рж░рж╢рж╛ржЗрж▓ (ржкрзБрж░рж╛рждржи)", "category": "ржЪрж╛рж▓", "price": 85, "image": "ЁЯНЪ", "origin": "ржжрж┐ржирж╛ржЬржкрзБрж░", "stock": "рзйрзжрзжрзж ржХрзЗржЬрж┐", "rating": 4 },
  { "id": 3, "name": "ржЪрж┐ржирж┐ржЧрзБрзЬрж╛ рж╕рзБржЧржирзНржзрж┐ ржЪрж╛рж▓", "category": "ржЪрж╛рж▓", "price": 155, "image": "тЬи", "origin": "ржмржЧрзБрзЬрж╛", "stock": "рззрзжрзжрзж ржХрзЗржЬрж┐", "rating": 5 },
  { "id": 4, "name": "ржмрж╛рж╕ржорждрзА ржЪрж╛рж▓ (рж▓ржВ)", "category": "ржЪрж╛рж▓", "price": 240, "image": "ЁЯМ╛", "origin": "ржнрж╛рж░ржд", "stock": "рзлрзжрзж ржХрзЗржЬрж┐", "rating": 5 },
  { "id": 5, "name": "ржмрж┐ржЖрж░-рзирзо ржЪрж╛рж▓", "category": "ржЪрж╛рж▓", "price": 62, "image": "ЁЯНЪ", "origin": "рж╢рзЗрж░ржкрзБрж░", "stock": "рзнрзжрзжрзж ржХрзЗржЬрж┐", "rating": 4 },
  { "id": 6, "name": "ржЦрж╛ржБржЯрж┐ рж╕рж░рж┐рж╖рж╛рж░ рждрзЗрж▓", "category": "рждрзЗрж▓", "price": 210, "image": "ЁЯН╢", "origin": "рж░рж╛ржЬрж╢рж╛рж╣рзА", "stock": "рзкрзжрзж рж▓рж┐ржЯрж╛рж░", "rating": 5 },
  { "id": 7, "name": "ржжрзЗрж╢рж┐ ржорж╕рзБрж░ ржбрж╛рж▓", "category": "ржбрж╛рж▓", "price": 135, "image": "ЁЯег", "origin": "ржХрзБрж╖рзНржЯрж┐рзЯрж╛", "stock": "рззрзирзжрзж ржХрзЗржЬрж┐", "rating": 4 },
  { "id": 8, "name": "ржЧрж╛ржУрзЯрж╛ ржШрж┐ (ржЦрж╛ржБржЯрж┐)", "category": "ржжрзБржЧрзНржзржЬрж╛ржд", "price": 1250, "image": "ЁЯНп", "origin": "ржкрж╛ржмржирж╛", "stock": "рзорзж ржХрзЗржЬрж┐", "rating": 5 },
  { "id": 9, "name": "ржХрж╛рж▓рзЛ ржЬрж┐рж░рж╛", "category": "ржмрзАржЬ", "price": 450, "image": "тЪл", "origin": "ржирж╛ржЯрзЛрж░", "stock": "рззрзжрзж ржХрзЗржЬрж┐", "rating": 5 }
]